<?xml version="1.0" encoding="UTF-8"?>
<!DOCTYPE plist PUBLIC "-//Apple//DTD PLIST 1.0//EN" "http://www.apple.com/DTDs/PropertyList-1.0.dtd"/>

<plist version="1.0">
    <dict>
        <key>ROOT</key>
        <array>
            <dict>
                <key>id</key>
                <string>120</string>
                <key>className</key>
                <string>PTModelObjectImage</string>
                <key>Name</key>
                <dict>
                    <key>value</key>
                    <string>Untitled</string>
                </dict>
                <key>Position</key>
                <dict>
                    <key>value</key>
                    <string>{0.000,0.000}</string>
                </dict>
                <key>Scale</key>
                <dict>
                    <key>value</key>
                    <string>{1.000,1.000}</string>
                </dict>
                <key>Hidden</key>
                <dict>
                    <key>visible</key>
                    <string>0</string>
                </dict>
                <key>Locked</key>
                <dict>
                    <key>visible</key>
                    <string>0</string>
                </dict>
                <key>Stick To Edge</key>
                <dict>
                    <key>value</key>
                    <string>0</string>
                </dict>
                <key>zDepth</key>
                <string>0</string>
            </dict>
            <dict>
                <key>id</key>
                <string>576</string>
                <key>className</key>
                <string>PTModelObjectImage</string>
                <key>Name</key>
                <dict>
                    <key>value</key>
                    <string>Untitled</string>
                </dict>
                <key>Position</key>
                <dict>
                    <key>value</key>
                    <string>{0.000,0.000}</string>
                </dict>
                <key>Scale</key>
                <dict>
                    <key>value</key>
                    <string>{1.000,1.000}</string>
                </dict>
                <key>Hidden</key>
                <dict>
                    <key>visible</key>
                    <string>0</string>
                </dict>
                <key>Locked</key>
                <dict>
                    <key>visible</key>
                    <string>0</string>
                </dict>
                <key>zDepth</key>
                <string>0</string>
            </dict>
            <dict>
                <key>id</key>
                <string>613</string>
                <key>className</key>
                <string>PTModelObjectImage</string>
                <key>Name</key>
                <dict>
                    <key>value</key>
                    <string>Untitled</string>
                </dict>
                <key>Position</key>
                <dict>
                    <key>value</key>
                    <string>{0.000,0.000}</string>
                    <key>animationsX</key>
                    <array/>
                    <key>animationsY</key>
                    <array/>
                </dict>
                <key>Rotation</key>
                <dict>
                    <key>animations</key>
                    <array/>
                </dict>
                <key>Scale</key>
                <dict>
                    <key>value</key>
                    <string>{1.000,1.000}</string>
                    <key>animationsX</key>
                    <array/>
                    <key>animationsY</key>
                    <array/>
                </dict>
                <key>Hidden</key>
                <dict>
                    <key>visible</key>
                    <string>0</string>
                </dict>
                <key>Locked</key>
                <dict>
                    <key>visible</key>
                    <string>0</string>
                </dict>
                <key>Opacity</key>
                <dict>
                    <key>animations</key>
                    <array/>
                </dict>
                <key>Stick To Edge</key>
                <dict>
                    <key>value</key>
                    <string>0</string>
                </dict>
                <key>zDepth</key>
                <string>0</string>
            </dict>
            <dict>
                <key>id</key>
                <string>656</string>
                <key>className</key>
                <string>PTModelObjectImage</string>
                <key>Name</key>
                <dict>
                    <key>value</key>
                    <string>Untitled</string>
                </dict>
                <key>Position</key>
                <dict>
                    <key>value</key>
                    <string>{0.000,0.000}</string>
                </dict>
                <key>Scale</key>
                <dict>
                    <key>value</key>
                    <string>{1.000,1.000}</string>
                </dict>
                <key>Hidden</key>
                <dict>
                    <key>visible</key>
                    <string>0</string>
                </dict>
                <key>Locked</key>
                <dict>
                    <key>visible</key>
                    <string>0</string>
                </dict>
                <key>Stick To Edge</key>
                <dict>
                    <key>value</key>
                    <string>0</string>
                </dict>
                <key>zDepth</key>
                <string>0</string>
            </dict>
            <dict>
                <key>id</key>
                <string>761</string>
                <key>className</key>
                <string>PTModelObjectImage</string>
                <key>Name</key>
                <dict>
                    <key>value</key>
                    <string>Untitled</string>
                </dict>
                <key>Position</key>
                <dict>
                    <key>value</key>
                    <string>{0.000,0.000}</string>
                    <key>animationsX</key>
                    <array/>
                    <key>animationsY</key>
                    <array/>
                </dict>
                <key>Rotation</key>
                <dict>
                    <key>animations</key>
                    <array/>
                </dict>
                <key>Scale</key>
                <dict>
                    <key>value</key>
                    <string>{1.000,1.000}</string>
                    <key>animationsX</key>
                    <array/>
                    <key>animationsY</key>
                    <array/>
                </dict>
                <key>Hidden</key>
                <dict>
                    <key>visible</key>
                    <string>0</string>
                </dict>
                <key>Locked</key>
                <dict>
                    <key>visible</key>
                    <string>0</string>
                </dict>
                <key>Opacity</key>
                <dict>
                    <key>animations</key>
                    <array/>
                </dict>
                <key>Stick To Edge</key>
                <dict>
                    <key>value</key>
                    <string>0</string>
                </dict>
                <key>zDepth</key>
                <string>0</string>
            </dict>
            <dict>
                <key>id</key>
                <string>1359</string>
                <key>className</key>
                <string>PTModelObjectImage</string>
                <key>Name</key>
                <dict>
                    <key>value</key>
                    <string>Untitled</string>
                </dict>
                <key>Position</key>
                <dict>
                    <key>value</key>
                    <string>{0.000,0.000}</string>
                    <key>animationsX</key>
                    <array/>
                    <key>animationsY</key>
                    <array/>
                </dict>
                <key>Rotation</key>
                <dict>
                    <key>animations</key>
                    <array/>
                </dict>
                <key>Scale</key>
                <dict>
                    <key>value</key>
                    <string>{1.000,1.000}</string>
                    <key>animationsX</key>
                    <array/>
                    <key>animationsY</key>
                    <array/>
                </dict>
                <key>Hidden</key>
                <dict>
                    <key>visible</key>
                    <string>0</string>
                </dict>
                <key>Locked</key>
                <dict>
                    <key>visible</key>
                    <string>0</string>
                </dict>
                <key>Opacity</key>
                <dict>
                    <key>animations</key>
                    <array/>
                </dict>
                <key>Stick To Edge</key>
                <dict>
                    <key>value</key>
                    <string>0</string>
                </dict>
                <key>zDepth</key>
                <string>0</string>
            </dict>
            <dict>
                <key>id</key>
                <string>1854</string>
                <key>className</key>
                <string>PTModelObjectImage</string>
                <key>Name</key>
                <dict>
                    <key>value</key>
                    <string>Untitled</string>
                </dict>
                <key>Position</key>
                <dict>
                    <key>value</key>
                    <string>{0.000,0.000}</string>
                </dict>
                <key>Scale</key>
                <dict>
                    <key>value</key>
                    <string>{1.000,1.000}</string>
                </dict>
                <key>Hidden</key>
                <dict>
                    <key>visible</key>
                    <string>0</string>
                </dict>
                <key>Locked</key>
                <dict>
                    <key>visible</key>
                    <string>0</string>
                </dict>
                <key>zDepth</key>
                <string>0</string>
            </dict>
            <dict>
                <key>id</key>
                <string>2066</string>
                <key>className</key>
                <string>PTModelObjectImage</string>
                <key>Name</key>
                <dict>
                    <key>value</key>
                    <string>Untitled</string>
                </dict>
                <key>Position</key>
                <dict>
                    <key>value</key>
                    <string>{0.000,0.000}</string>
                    <key>animationsX</key>
                    <array/>
                    <key>animationsY</key>
                    <array/>
                </dict>
                <key>Rotation</key>
                <dict>
                    <key>animations</key>
                    <array/>
                </dict>
                <key>Scale</key>
                <dict>
                    <key>value</key>
                    <string>{1.000,1.000}</string>
                    <key>animationsX</key>
                    <array/>
                    <key>animationsY</key>
                    <array/>
                </dict>
                <key>Hidden</key>
                <dict>
                    <key>visible</key>
                    <string>0</string>
                </dict>
                <key>Locked</key>
                <dict>
                    <key>visible</key>
                    <string>0</string>
                </dict>
                <key>Opacity</key>
                <dict>
                    <key>animations</key>
                    <array/>
                </dict>
                <key>Stick To Edge</key>
                <dict>
                    <key>value</key>
                    <string>0</string>
                </dict>
                <key>zDepth</key>
                <string>0</string>
            </dict>
            <dict>
                <key>id</key>
                <string>2639</string>
                <key>className</key>
                <string>PTModelObjectImage</string>
                <key>Name</key>
                <dict>
                    <key>value</key>
                    <string>Untitled</string>
                </dict>
                <key>Position</key>
                <dict>
                    <key>value</key>
                    <string>{207.569,269.292}</string>
                    <key>useDefault</key>
                    <string>0</string>
                    <key>animationsX</key>
                    <array>
                        <dict>
                            <key>state</key>
                            <string>1</string>
                            <key>animation</key>
                            <dict>
                                <key>points</key>
                                <array/>
                                <key>preset</key>
                                <string>4</string>
                            </dict>
                        </dict>
                    </array>
                    <key>animationsY</key>
                    <array>
                        <dict>
                            <key>state</key>
                            <string>1</string>
                            <key>animation</key>
                            <dict>
                                <key>points</key>
                                <array/>
                                <key>preset</key>
                                <string>4</string>
                            </dict>
                        </dict>
                    </array>
                </dict>
                <key>Rotation</key>
                <dict>
                    <key>animations</key>
                    <array/>
                </dict>
                <key>Scale</key>
                <dict>
                    <key>value</key>
                    <string>{0.565,0.565}</string>
                    <key>useDefault</key>
                    <string>0</string>
                    <key>animationsX</key>
                    <array/>
                    <key>animationsY</key>
                    <array/>
                </dict>
                <key>Hidden</key>
                <dict>
                    <key>visible</key>
                    <string>0</string>
                </dict>
                <key>Locked</key>
                <dict>
                    <key>visible</key>
                    <string>0</string>
                </dict>
                <key>Opacity</key>
                <dict>
                    <key>animations</key>
                    <array/>
                </dict>
                <key>zDepth</key>
                <string>8</string>
            </dict>
            <dict>
                <key>id</key>
                <string>2666</string>
                <key>className</key>
                <string>PTModelObjectImage</string>
                <key>Name</key>
                <dict>
                    <key>value</key>
                    <string>Untitled</string>
                </dict>
                <key>Position</key>
                <dict>
                    <key>value</key>
                    <string>{555.676,331.020}</string>
                    <key>useDefault</key>
                    <string>0</string>
                    <key>animationsX</key>
                    <array/>
                    <key>animationsY</key>
                    <array/>
                </dict>
                <key>Rotation</key>
                <dict>
                    <key>animations</key>
                    <array/>
                </dict>
                <key>Scale</key>
                <dict>
                    <key>value</key>
                    <string>{1.483,1.483}</string>
                    <key>useDefault</key>
                    <string>0</string>
                    <key>animationsX</key>
                    <array/>
                    <key>animationsY</key>
                    <array/>
                </dict>
                <key>Hidden</key>
                <dict>
                    <key>visible</key>
                    <string>0</string>
                </dict>
                <key>Locked</key>
                <dict>
                    <key>visible</key>
                    <string>0</string>
                </dict>
                <key>Opacity</key>
                <dict>
                    <key>animations</key>
                    <array/>
                </dict>
                <key>zDepth</key>
                <string>4</string>
            </dict>
            <dict>
                <key>id</key>
                <string>2712</string>
                <key>className</key>
                <string>PTModelObjectImage</string>
                <key>Name</key>
                <dict>
                    <key>value</key>
                    <string>Untitled</string>
                </dict>
                <key>Position</key>
                <dict>
                    <key>value</key>
                    <string>{281.229,585.854}</string>
                    <key>useDefault</key>
                    <string>0</string>
                    <key>animationsX</key>
                    <array/>
                    <key>animationsY</key>
                    <array/>
                </dict>
                <key>Rotation</key>
                <dict>
                    <key>animations</key>
                    <array/>
                </dict>
                <key>Scale</key>
                <dict>
                    <key>value</key>
                    <string>{0.800,0.800}</string>
                    <key>useDefault</key>
                    <string>0</string>
                    <key>animationsX</key>
                    <array/>
                    <key>animationsY</key>
                    <array/>
                </dict>
                <key>Hidden</key>
                <dict>
                    <key>visible</key>
                    <string>0</string>
                </dict>
                <key>Locked</key>
                <dict>
                    <key>visible</key>
                    <string>0</string>
                </dict>
                <key>Opacity</key>
                <dict>
                    <key>animations</key>
                    <array/>
                </dict>
                <key>Stick To Edge</key>
                <dict>
                    <key>value</key>
                    <string>0</string>
                </dict>
                <key>zDepth</key>
                <string>0</string>
            </dict>
            <dict>
                <key>id</key>
                <string>2776</string>
                <key>className</key>
                <string>PTModelObjectImage</string>
                <key>Name</key>
                <dict>
                    <key>value</key>
                    <string>Untitled</string>
                </dict>
                <key>Position</key>
                <dict>
                    <key>value</key>
                    <string>{568.000,205.015}</string>
                    <key>useDefault</key>
                    <string>0</string>
                    <key>animationsX</key>
                    <array/>
                    <key>animationsY</key>
                    <array/>
                </dict>
                <key>Rotation</key>
                <dict>
                    <key>animations</key>
                    <array/>
                </dict>
                <key>Scale</key>
                <dict>
                    <key>value</key>
                    <string>{0.700,0.700}</string>
                    <key>useDefault</key>
                    <string>0</string>
                    <key>animationsX</key>
                    <array/>
                    <key>animationsY</key>
                    <array/>
                </dict>
                <key>Hidden</key>
                <dict>
                    <key>visible</key>
                    <string>0</string>
                </dict>
                <key>Locked</key>
                <dict>
                    <key>visible</key>
                    <string>0</string>
                </dict>
                <key>Opacity</key>
                <dict>
                    <key>animations</key>
                    <array/>
                </dict>
                <key>zDepth</key>
                <string>2</string>
            </dict>
            <dict>
                <key>id</key>
                <string>2794</string>
                <key>className</key>
                <string>PTModelObjectImage</string>
                <key>Name</key>
                <dict>
                    <key>value</key>
                    <string>Untitled</string>
                </dict>
                <key>Position</key>
                <dict>
                    <key>value</key>
                    <string>{568.000,475.544}</string>
                    <key>useDefault</key>
                    <string>0</string>
                    <key>animationsX</key>
                    <array/>
                    <key>animationsY</key>
                    <array/>
                </dict>
                <key>Rotation</key>
                <dict>
                    <key>animations</key>
                    <array/>
                </dict>
                <key>Scale</key>
                <dict>
                    <key>value</key>
                    <string>{0.337,0.337}</string>
                    <key>useDefault</key>
                    <string>0</string>
                    <key>animationsX</key>
                    <array/>
                    <key>animationsY</key>
                    <array/>
                </dict>
                <key>Hidden</key>
                <dict>
                    <key>visible</key>
                    <string>0</string>
                </dict>
                <key>Locked</key>
                <dict>
                    <key>visible</key>
                    <string>0</string>
                </dict>
                <key>Opacity</key>
                <dict>
                    <key>animations</key>
                    <array/>
                </dict>
                <key>zDepth</key>
                <string>5</string>
            </dict>
            <dict>
                <key>id</key>
                <string>2912</string>
                <key>className</key>
                <string>PTModelObjectImage</string>
                <key>Name</key>
                <dict>
                    <key>value</key>
                    <string>Untitled</string>
                </dict>
                <key>Position</key>
                <dict>
                    <key>value</key>
                    <string>{937.470,182.368}</string>
                    <key>useDefault</key>
                    <string>0</string>
                    <key>animationsX</key>
                    <array/>
                    <key>animationsY</key>
                    <array/>
                </dict>
                <key>Rotation</key>
                <dict>
                    <key>value</key>
                    <string>0.525168</string>
                    <key>useDefault</key>
                    <string>0</string>
                    <key>animations</key>
                    <array/>
                </dict>
                <key>Scale</key>
                <dict>
                    <key>value</key>
                    <string>{-0.600,0.637}</string>
                    <key>useDefault</key>
                    <string>0</string>
                    <key>animationsX</key>
                    <array/>
                    <key>animationsY</key>
                    <array/>
                </dict>
                <key>Hidden</key>
                <dict>
                    <key>visible</key>
                    <string>0</string>
                </dict>
                <key>Locked</key>
                <dict>
                    <key>visible</key>
                    <string>0</string>
                </dict>
                <key>Opacity</key>
                <dict>
                    <key>animations</key>
                    <array/>
                </dict>
                <key>zDepth</key>
                <string>7</string>
            </dict>
            <dict>
                <key>id</key>
                <string>3000</string>
                <key>className</key>
                <string>PTModelObjectImage</string>
                <key>Name</key>
                <dict>
                    <key>value</key>
                    <string>Untitled</string>
                </dict>
                <key>Position</key>
                <dict>
                    <key>value</key>
                    <string>{710.693,583.624}</string>
                    <key>useDefault</key>
                    <string>0</string>
                    <key>animationsX</key>
                    <array/>
                    <key>animationsY</key>
                    <array/>
                </dict>
                <key>Rotation</key>
                <dict>
                    <key>animations</key>
                    <array/>
                </dict>
                <key>Scale</key>
                <dict>
                    <key>value</key>
                    <string>{0.700,0.700}</string>
                    <key>useDefault</key>
                    <string>0</string>
                    <key>animationsX</key>
                    <array/>
                    <key>animationsY</key>
                    <array/>
                </dict>
                <key>Hidden</key>
                <dict>
                    <key>visible</key>
                    <string>0</string>
                </dict>
                <key>Locked</key>
                <dict>
                    <key>visible</key>
                    <string>0</string>
                </dict>
                <key>Opacity</key>
                <dict>
                    <key>animations</key>
                    <array/>
                </dict>
                <key>Stick To Edge</key>
                <dict>
                    <key>value</key>
                    <string>0</string>
                </dict>
                <key>zDepth</key>
                <string>3</string>
            </dict>
            <dict>
                <key>id</key>
                <string>3012</string>
                <key>className</key>
                <string>PTModelObjectImage</string>
                <key>Name</key>
                <dict>
                    <key>value</key>
                    <string>Untitled</string>
                </dict>
                <key>Position</key>
                <dict>
                    <key>value</key>
                    <string>{535.727,585.000}</string>
                    <key>useDefault</key>
                    <string>0</string>
                    <key>animationsX</key>
                    <array/>
                    <key>animationsY</key>
                    <array/>
                </dict>
                <key>Rotation</key>
                <dict>
                    <key>animations</key>
                    <array/>
                </dict>
                <key>Scale</key>
                <dict>
                    <key>value</key>
                    <string>{0.800,0.800}</string>
                    <key>useDefault</key>
                    <string>0</string>
                    <key>animationsX</key>
                    <array/>
                    <key>animationsY</key>
                    <array/>
                </dict>
                <key>Hidden</key>
                <dict>
                    <key>visible</key>
                    <string>0</string>
                </dict>
                <key>Locked</key>
                <dict>
                    <key>visible</key>
                    <string>0</string>
                </dict>
                <key>Opacity</key>
                <dict>
                    <key>animations</key>
                    <array/>
                </dict>
                <key>Stick To Edge</key>
                <dict>
                    <key>value</key>
                    <string>0</string>
                </dict>
                <key>zDepth</key>
                <string>2</string>
            </dict>
            <dict>
                <key>id</key>
                <string>3863</string>
                <key>className</key>
                <string>PTModelObjectImage</string>
                <key>Name</key>
                <dict>
                    <key>value</key>
                    <string>Untitled</string>
                </dict>
                <key>Position</key>
                <dict>
                    <key>value</key>
                    <string>{0.000,0.000}</string>
                    <key>animationsX</key>
                    <array/>
                    <key>animationsY</key>
                    <array/>
                </dict>
                <key>Rotation</key>
                <dict>
                    <key>animations</key>
                    <array/>
                </dict>
                <key>Scale</key>
                <dict>
                    <key>value</key>
                    <string>{1.000,1.000}</string>
                    <key>animationsX</key>
                    <array/>
                    <key>animationsY</key>
                    <array/>
                </dict>
                <key>Hidden</key>
                <dict>
                    <key>visible</key>
                    <string>0</string>
                </dict>
                <key>Locked</key>
                <dict>
                    <key>visible</key>
                    <string>0</string>
                </dict>
                <key>Opacity</key>
                <dict>
                    <key>animations</key>
                    <array/>
                </dict>
                <key>Stick To Edge</key>
                <dict>
                    <key>value</key>
                    <string>0</string>
                </dict>
                <key>zDepth</key>
                <string>0</string>
            </dict>
            <dict>
                <key>id</key>
                <string>4452</string>
                <key>className</key>
                <string>PTModelObjectImage</string>
                <key>Name</key>
                <dict>
                    <key>value</key>
                    <string>Untitled</string>
                </dict>
                <key>Position</key>
                <dict>
                    <key>value</key>
                    <string>{571.285,275.094}</string>
                    <key>useDefault</key>
                    <string>0</string>
                    <key>animationsX</key>
                    <array/>
                    <key>animationsY</key>
                    <array/>
                </dict>
                <key>Rotation</key>
                <dict>
                    <key>animations</key>
                    <array/>
                </dict>
                <key>Scale</key>
                <dict>
                    <key>value</key>
                    <string>{1.386,1.386}</string>
                    <key>useDefault</key>
                    <string>0</string>
                    <key>animationsX</key>
                    <array/>
                    <key>animationsY</key>
                    <array/>
                </dict>
                <key>Hidden</key>
                <dict>
                    <key>visible</key>
                    <string>0</string>
                </dict>
                <key>Locked</key>
                <dict>
                    <key>visible</key>
                    <string>0</string>
                </dict>
                <key>zDepth</key>
                <string>3</string>
            </dict>
            <dict>
                <key>id</key>
                <string>4564</string>
                <key>className</key>
                <string>PTModelObjectImage</string>
                <key>Name</key>
                <dict>
                    <key>value</key>
                    <string>Untitled</string>
                </dict>
                <key>Position</key>
                <dict>
                    <key>value</key>
                    <string>{0.000,0.000}</string>
                    <key>animationsX</key>
                    <array/>
                    <key>animationsY</key>
                    <array/>
                </dict>
                <key>Rotation</key>
                <dict>
                    <key>animations</key>
                    <array/>
                </dict>
                <key>Scale</key>
                <dict>
                    <key>value</key>
                    <string>{1.000,1.000}</string>
                    <key>animationsX</key>
                    <array/>
                    <key>animationsY</key>
                    <array/>
                </dict>
                <key>Hidden</key>
                <dict>
                    <key>visible</key>
                    <string>0</string>
                </dict>
                <key>Locked</key>
                <dict>
                    <key>visible</key>
                    <string>0</string>
                </dict>
                <key>Opacity</key>
                <dict>
                    <key>animations</key>
                    <array/>
                </dict>
                <key>Stick To Edge</key>
                <dict>
                    <key>value</key>
                    <string>0</string>
                </dict>
                <key>zDepth</key>
                <string>0</string>
            </dict>
            <dict>
                <key>id</key>
                <string>5584</string>
                <key>className</key>
                <string>PTModelObjectImage</string>
                <key>Name</key>
                <dict>
                    <key>value</key>
                    <string>Untitled</string>
                </dict>
                <key>Position</key>
                <dict>
                    <key>value</key>
                    <string>{568.000,281.000}</string>
                    <key>useDefault</key>
                    <string>0</string>
                    <key>animationsX</key>
                    <array/>
                    <key>animationsY</key>
                    <array/>
                </dict>
                <key>Rotation</key>
                <dict>
                    <key>animations</key>
                    <array/>
                </dict>
                <key>Scale</key>
                <dict>
                    <key>value</key>
                    <string>{1.000,1.000}</string>
                    <key>animationsX</key>
                    <array/>
                    <key>animationsY</key>
                    <array/>
                </dict>
                <key>Hidden</key>
                <dict>
                    <key>visible</key>
                    <string>0</string>
                </dict>
                <key>Locked</key>
                <dict>
                    <key>visible</key>
                    <string>0</string>
                </dict>
                <key>Opacity</key>
                <dict>
                    <key>animations</key>
                    <array/>
                </dict>
                <key>zDepth</key>
                <string>2</string>
            </dict>
            <dict>
                <key>id</key>
                <string>5787</string>
                <key>className</key>
                <string>PTModelObjectImage</string>
                <key>Name</key>
                <dict>
                    <key>value</key>
                    <string>Untitled</string>
                </dict>
                <key>Position</key>
                <dict>
                    <key>value</key>
                    <string>{0.000,0.000}</string>
                </dict>
                <key>Scale</key>
                <dict>
                    <key>value</key>
                    <string>{1.000,1.000}</string>
                </dict>
                <key>Hidden</key>
                <dict>
                    <key>visible</key>
                    <string>0</string>
                </dict>
                <key>Locked</key>
                <dict>
                    <key>visible</key>
                    <string>0</string>
                </dict>
                <key>zDepth</key>
                <string>0</string>
            </dict>
            <dict>
                <key>id</key>
                <string>5828</string>
                <key>className</key>
                <string>PTModelObjectImage</string>
                <key>Name</key>
                <dict>
                    <key>value</key>
                    <string>Untitled</string>
                </dict>
                <key>Position</key>
                <dict>
                    <key>value</key>
                    <string>{0.000,0.000}</string>
                </dict>
                <key>Scale</key>
                <dict>
                    <key>value</key>
                    <string>{1.000,1.000}</string>
                </dict>
                <key>Hidden</key>
                <dict>
                    <key>visible</key>
                    <string>0</string>
                </dict>
                <key>Locked</key>
                <dict>
                    <key>visible</key>
                    <string>0</string>
                </dict>
                <key>Stick To Edge</key>
                <dict>
                    <key>value</key>
                    <string>0</string>
                </dict>
                <key>zDepth</key>
                <string>0</string>
            </dict>
            <dict>
                <key>id</key>
                <string>5856</string>
                <key>className</key>
                <string>PTModelObjectImage</string>
                <key>Name</key>
                <dict>
                    <key>value</key>
                    <string>Untitled</string>
                </dict>
                <key>Position</key>
                <dict>
                    <key>value</key>
                    <string>{0.000,0.000}</string>
                </dict>
                <key>Scale</key>
                <dict>
                    <key>value</key>
                    <string>{1.000,1.000}</string>
                </dict>
                <key>Hidden</key>
                <dict>
                    <key>visible</key>
                    <string>0</string>
                </dict>
                <key>Locked</key>
                <dict>
                    <key>visible</key>
                    <string>0</string>
                </dict>
                <key>Stick To Edge</key>
                <dict>
                    <key>value</key>
                    <string>0</string>
                </dict>
                <key>zDepth</key>
                <string>0</string>
            </dict>
            <dict>
                <key>id</key>
                <string>5867</string>
                <key>className</key>
                <string>PTModelObjectImage</string>
                <key>Name</key>
                <dict>
                    <key>value</key>
                    <string>Untitled</string>
                </dict>
                <key>Position</key>
                <dict>
                    <key>value</key>
                    <string>{0.000,0.000}</string>
                </dict>
                <key>Scale</key>
                <dict>
                    <key>value</key>
                    <string>{1.000,1.000}</string>
                </dict>
                <key>Hidden</key>
                <dict>
                    <key>visible</key>
                    <string>0</string>
                </dict>
                <key>Locked</key>
                <dict>
                    <key>visible</key>
                    <string>0</string>
                </dict>
                <key>Stick To Edge</key>
                <dict>
                    <key>value</key>
                    <string>0</string>
                </dict>
                <key>zDepth</key>
                <string>0</string>
            </dict>
            <dict>
                <key>id</key>
                <string>6066</string>
                <key>className</key>
                <string>PTModelObjectImage</string>
                <key>Name</key>
                <dict>
                    <key>value</key>
                    <string>Untitled</string>
                </dict>
                <key>Position</key>
                <dict>
                    <key>value</key>
                    <string>{0.000,0.000}</string>
                    <key>animationsX</key>
                    <array/>
                    <key>animationsY</key>
                    <array/>
                </dict>
                <key>Rotation</key>
                <dict>
                    <key>animations</key>
                    <array/>
                </dict>
                <key>Scale</key>
                <dict>
                    <key>value</key>
                    <string>{2.000,2.000}</string>
                    <key>useDefault</key>
                    <string>0</string>
                    <key>animationsX</key>
                    <array/>
                    <key>animationsY</key>
                    <array/>
                </dict>
                <key>Hidden</key>
                <dict>
                    <key>visible</key>
                    <string>0</string>
                </dict>
                <key>Locked</key>
                <dict>
                    <key>visible</key>
                    <string>0</string>
                </dict>
                <key>Opacity</key>
                <dict>
                    <key>animations</key>
                    <array/>
                </dict>
                <key>Stick To Edge</key>
                <dict>
                    <key>value</key>
                    <string>0</string>
                </dict>
                <key>zDepth</key>
                <string>0</string>
            </dict>
            <dict>
                <key>id</key>
                <string>6075</string>
                <key>className</key>
                <string>PTModelObjectImage</string>
                <key>Name</key>
                <dict>
                    <key>value</key>
                    <string>Untitled</string>
                </dict>
                <key>Position</key>
                <dict>
                    <key>value</key>
                    <string>{0.000,0.000}</string>
                    <key>animationsX</key>
                    <array/>
                    <key>animationsY</key>
                    <array/>
                </dict>
                <key>Rotation</key>
                <dict>
                    <key>animations</key>
                    <array/>
                </dict>
                <key>Scale</key>
                <dict>
                    <key>value</key>
                    <string>{0.600,0.600}</string>
                    <key>useDefault</key>
                    <string>0</string>
                    <key>animationsX</key>
                    <array/>
                    <key>animationsY</key>
                    <array/>
                </dict>
                <key>Hidden</key>
                <dict>
                    <key>visible</key>
                    <string>0</string>
                </dict>
                <key>Locked</key>
                <dict>
                    <key>visible</key>
                    <string>0</string>
                </dict>
                <key>Opacity</key>
                <dict>
                    <key>animations</key>
                    <array/>
                </dict>
                <key>Stick To Edge</key>
                <dict>
                    <key>value</key>
                    <string>0</string>
                </dict>
                <key>zDepth</key>
                <string>0</string>
            </dict>
            <dict>
                <key>id</key>
                <string>6094</string>
                <key>className</key>
                <string>PTModelObjectImage</string>
                <key>Name</key>
                <dict>
                    <key>value</key>
                    <string>Untitled</string>
                </dict>
                <key>Position</key>
                <dict>
                    <key>value</key>
                    <string>{0.000,0.000}</string>
                    <key>animationsX</key>
                    <array/>
                    <key>animationsY</key>
                    <array/>
                </dict>
                <key>Rotation</key>
                <dict>
                    <key>animations</key>
                    <array/>
                </dict>
                <key>Scale</key>
                <dict>
                    <key>value</key>
                    <string>{1.000,1.000}</string>
                    <key>animationsX</key>
                    <array/>
                    <key>animationsY</key>
                    <array/>
                </dict>
                <key>Hidden</key>
                <dict>
                    <key>visible</key>
                    <string>0</string>
                </dict>
                <key>Locked</key>
                <dict>
                    <key>visible</key>
                    <string>0</string>
                </dict>
                <key>Opacity</key>
                <dict>
                    <key>animations</key>
                    <array/>
                </dict>
                <key>Stick To Edge</key>
                <dict>
                    <key>value</key>
                    <string>0</string>
                </dict>
                <key>zDepth</key>
                <string>0</string>
            </dict>
            <dict>
                <key>id</key>
                <string>6394</string>
                <key>className</key>
                <string>PTModelObjectImage</string>
                <key>Name</key>
                <dict>
                    <key>value</key>
                    <string>Untitled</string>
                </dict>
                <key>Position</key>
                <dict>
                    <key>value</key>
                    <string>{568.000,323.344}</string>
                    <key>useDefault</key>
                    <string>0</string>
                    <key>animationsX</key>
                    <array/>
                    <key>animationsY</key>
                    <array/>
                </dict>
                <key>Rotation</key>
                <dict>
                    <key>animations</key>
                    <array/>
                </dict>
                <key>Scale</key>
                <dict>
                    <key>value</key>
                    <string>{1.000,1.000}</string>
                    <key>animationsX</key>
                    <array/>
                    <key>animationsY</key>
                    <array/>
                </dict>
                <key>Hidden</key>
                <dict>
                    <key>visible</key>
                    <string>0</string>
                </dict>
                <key>Locked</key>
                <dict>
                    <key>visible</key>
                    <string>0</string>
                </dict>
                <key>Opacity</key>
                <dict>
                    <key>animations</key>
                    <array/>
                </dict>
                <key>zDepth</key>
                <string>4</string>
            </dict>
            <dict>
                <key>id</key>
                <string>6399</string>
                <key>className</key>
                <string>PTModelObjectImage</string>
                <key>Name</key>
                <dict>
                    <key>value</key>
                    <string>Untitled</string>
                </dict>
                <key>Position</key>
                <dict>
                    <key>value</key>
                    <string>{562.000,500.566}</string>
                    <key>useDefault</key>
                    <string>0</string>
                    <key>animationsX</key>
                    <array/>
                    <key>animationsY</key>
                    <array/>
                </dict>
                <key>Rotation</key>
                <dict>
                    <key>animations</key>
                    <array/>
                </dict>
                <key>Scale</key>
                <dict>
                    <key>value</key>
                    <string>{0.400,0.400}</string>
                    <key>useDefault</key>
                    <string>0</string>
                    <key>animationsX</key>
                    <array/>
                    <key>animationsY</key>
                    <array/>
                </dict>
                <key>Hidden</key>
                <dict>
                    <key>visible</key>
                    <string>0</string>
                </dict>
                <key>Locked</key>
                <dict>
                    <key>visible</key>
                    <string>0</string>
                </dict>
                <key>Opacity</key>
                <dict>
                    <key>animations</key>
                    <array/>
                </dict>
                <key>zDepth</key>
                <string>5</string>
            </dict>
            <dict>
                <key>id</key>
                <string>6409</string>
                <key>className</key>
                <string>PTModelObjectImage</string>
                <key>Name</key>
                <dict>
                    <key>value</key>
                    <string>Untitled</string>
                </dict>
                <key>Position</key>
                <dict>
                    <key>value</key>
                    <string>{561.963,58.571}</string>
                    <key>useDefault</key>
                    <string>0</string>
                    <key>animationsX</key>
                    <array/>
                    <key>animationsY</key>
                    <array/>
                </dict>
                <key>Rotation</key>
                <dict>
                    <key>animations</key>
                    <array/>
                </dict>
                <key>Scale</key>
                <dict>
                    <key>value</key>
                    <string>{1.239,1.239}</string>
                    <key>useDefault</key>
                    <string>0</string>
                    <key>animationsX</key>
                    <array/>
                    <key>animationsY</key>
                    <array/>
                </dict>
                <key>Hidden</key>
                <dict>
                    <key>visible</key>
                    <string>0</string>
                </dict>
                <key>Locked</key>
                <dict>
                    <key>visible</key>
                    <string>0</string>
                </dict>
                <key>Opacity</key>
                <dict>
                    <key>animations</key>
                    <array/>
                </dict>
                <key>zDepth</key>
                <string>0</string>
            </dict>
            <dict>
                <key>id</key>
                <string>6764</string>
                <key>className</key>
                <string>PTModelObjectImage</string>
                <key>Name</key>
                <dict>
                    <key>value</key>
                    <string>Untitled</string>
                </dict>
                <key>Position</key>
                <dict>
                    <key>value</key>
                    <string>{0.000,0.000}</string>
                </dict>
                <key>Scale</key>
                <dict>
                    <key>value</key>
                    <string>{1.000,1.000}</string>
                </dict>
                <key>Hidden</key>
                <dict>
                    <key>visible</key>
                    <string>0</string>
                </dict>
                <key>Locked</key>
                <dict>
                    <key>visible</key>
                    <string>0</string>
                </dict>
                <key>Stick To Edge</key>
                <dict>
                    <key>value</key>
                    <string>0</string>
                </dict>
                <key>zDepth</key>
                <string>0</string>
            </dict>
            <dict>
                <key>id</key>
                <string>6775</string>
                <key>className</key>
                <string>PTModelObjectImage</string>
                <key>Name</key>
                <dict>
                    <key>value</key>
                    <string>Untitled</string>
                </dict>
                <key>Position</key>
                <dict>
                    <key>value</key>
                    <string>{0.000,0.000}</string>
                </dict>
                <key>Scale</key>
                <dict>
                    <key>value</key>
                    <string>{1.000,1.000}</string>
                </dict>
                <key>Hidden</key>
                <dict>
                    <key>visible</key>
                    <string>0</string>
                </dict>
                <key>Locked</key>
                <dict>
                    <key>visible</key>
                    <string>0</string>
                </dict>
                <key>Stick To Edge</key>
                <dict>
                    <key>value</key>
                    <string>0</string>
                </dict>
                <key>zDepth</key>
                <string>0</string>
            </dict>
            <dict>
                <key>id</key>
                <string>6795</string>
                <key>className</key>
                <string>PTModelObjectImage</string>
                <key>Name</key>
                <dict>
                    <key>value</key>
                    <string>Untitled</string>
                </dict>
                <key>Position</key>
                <dict>
                    <key>value</key>
                    <string>{0.000,0.000}</string>
                </dict>
                <key>Scale</key>
                <dict>
                    <key>value</key>
                    <string>{1.000,1.000}</string>
                </dict>
                <key>Hidden</key>
                <dict>
                    <key>visible</key>
                    <string>0</string>
                </dict>
                <key>Locked</key>
                <dict>
                    <key>visible</key>
                    <string>0</string>
                </dict>
                <key>zDepth</key>
                <string>0</string>
            </dict>
            <dict>
                <key>id</key>
                <string>6807</string>
                <key>className</key>
                <string>PTModelObjectImage</string>
                <key>Name</key>
                <dict>
                    <key>value</key>
                    <string>Untitled</string>
                </dict>
                <key>Position</key>
                <dict>
                    <key>value</key>
                    <string>{0.000,0.000}</string>
                </dict>
                <key>Scale</key>
                <dict>
                    <key>value</key>
                    <string>{1.000,1.000}</string>
                </dict>
                <key>Hidden</key>
                <dict>
                    <key>visible</key>
                    <string>0</string>
                </dict>
                <key>Locked</key>
                <dict>
                    <key>visible</key>
                    <string>0</string>
                </dict>
                <key>Stick To Edge</key>
                <dict>
                    <key>value</key>
                    <string>0</string>
                </dict>
                <key>zDepth</key>
                <string>0</string>
            </dict>
            <dict>
                <key>id</key>
                <string>6819</string>
                <key>className</key>
                <string>PTModelObjectImage</string>
                <key>Name</key>
                <dict>
                    <key>value</key>
                    <string>Untitled</string>
                </dict>
                <key>Position</key>
                <dict>
                    <key>value</key>
                    <string>{0.000,0.000}</string>
                </dict>
                <key>Scale</key>
                <dict>
                    <key>value</key>
                    <string>{1.000,1.000}</string>
                </dict>
                <key>Hidden</key>
                <dict>
                    <key>visible</key>
                    <string>0</string>
                </dict>
                <key>Locked</key>
                <dict>
                    <key>visible</key>
                    <string>0</string>
                </dict>
                <key>Stick To Edge</key>
                <dict>
                    <key>value</key>
                    <string>0</string>
                </dict>
                <key>zDepth</key>
                <string>0</string>
            </dict>
            <dict>
                <key>id</key>
                <string>7010</string>
                <key>className</key>
                <string>PTModelObjectImage</string>
                <key>Name</key>
                <dict>
                    <key>value</key>
                    <string>Untitled</string>
                </dict>
                <key>Position</key>
                <dict>
                    <key>value</key>
                    <string>{568.000,56.976}</string>
                    <key>useDefault</key>
                    <string>0</string>
                    <key>animationsX</key>
                    <array/>
                    <key>animationsY</key>
                    <array/>
                </dict>
                <key>Rotation</key>
                <dict>
                    <key>animations</key>
                    <array/>
                </dict>
                <key>Scale</key>
                <dict>
                    <key>value</key>
                    <string>{1.263,1.263}</string>
                    <key>useDefault</key>
                    <string>0</string>
                    <key>animationsX</key>
                    <array/>
                    <key>animationsY</key>
                    <array/>
                </dict>
                <key>Hidden</key>
                <dict>
                    <key>visible</key>
                    <string>0</string>
                </dict>
                <key>Locked</key>
                <dict>
                    <key>visible</key>
                    <string>0</string>
                </dict>
                <key>zDepth</key>
                <string>2</string>
            </dict>
            <dict>
                <key>id</key>
                <string>7176</string>
                <key>className</key>
                <string>PTModelObjectImage</string>
                <key>Name</key>
                <dict>
                    <key>value</key>
                    <string>Untitled</string>
                </dict>
                <key>Position</key>
                <dict>
                    <key>value</key>
                    <string>{0.000,0.000}</string>
                </dict>
                <key>Scale</key>
                <dict>
                    <key>value</key>
                    <string>{1.000,1.000}</string>
                </dict>
                <key>Hidden</key>
                <dict>
                    <key>visible</key>
                    <string>0</string>
                </dict>
                <key>Locked</key>
                <dict>
                    <key>visible</key>
                    <string>0</string>
                </dict>
                <key>zDepth</key>
                <string>0</string>
            </dict>
            <dict>
                <key>id</key>
                <string>7404</string>
                <key>className</key>
                <string>PTModelObjectImage</string>
                <key>Name</key>
                <dict>
                    <key>value</key>
                    <string>Untitled</string>
                </dict>
                <key>Position</key>
                <dict>
                    <key>value</key>
                    <string>{568.000,54.972}</string>
                    <key>useDefault</key>
                    <string>0</string>
                    <key>animationsX</key>
                    <array/>
                    <key>animationsY</key>
                    <array/>
                </dict>
                <key>Rotation</key>
                <dict>
                    <key>animations</key>
                    <array/>
                </dict>
                <key>Scale</key>
                <dict>
                    <key>value</key>
                    <string>{1.129,1.129}</string>
                    <key>useDefault</key>
                    <string>0</string>
                    <key>animationsX</key>
                    <array/>
                    <key>animationsY</key>
                    <array/>
                </dict>
                <key>Hidden</key>
                <dict>
                    <key>visible</key>
                    <string>0</string>
                </dict>
                <key>Locked</key>
                <dict>
                    <key>visible</key>
                    <string>0</string>
                </dict>
                <key>Opacity</key>
                <dict>
                    <key>animations</key>
                    <array/>
                </dict>
                <key>zDepth</key>
                <string>5</string>
            </dict>
            <dict>
                <key>id</key>
                <string>7411</string>
                <key>className</key>
                <string>PTModelObjectImage</string>
                <key>Name</key>
                <dict>
                    <key>value</key>
                    <string>Untitled</string>
                </dict>
                <key>Position</key>
                <dict>
                    <key>value</key>
                    <string>{0.000,0.000}</string>
                    <key>animationsX</key>
                    <array/>
                    <key>animationsY</key>
                    <array/>
                </dict>
                <key>Rotation</key>
                <dict>
                    <key>animations</key>
                    <array/>
                </dict>
                <key>Scale</key>
                <dict>
                    <key>value</key>
                    <string>{1.000,1.000}</string>
                    <key>animationsX</key>
                    <array/>
                    <key>animationsY</key>
                    <array/>
                </dict>
                <key>Hidden</key>
                <dict>
                    <key>visible</key>
                    <string>0</string>
                </dict>
                <key>Locked</key>
                <dict>
                    <key>visible</key>
                    <string>0</string>
                </dict>
                <key>Opacity</key>
                <dict>
                    <key>animations</key>
                    <array/>
                </dict>
                <key>Stick To Edge</key>
                <dict>
                    <key>value</key>
                    <string>0</string>
                </dict>
                <key>zDepth</key>
                <string>0</string>
            </dict>
            <dict>
                <key>id</key>
                <string>7420</string>
                <key>className</key>
                <string>PTModelObjectImage</string>
                <key>Name</key>
                <dict>
                    <key>value</key>
                    <string>Untitled</string>
                </dict>
                <key>Position</key>
                <dict>
                    <key>value</key>
                    <string>{0.000,0.000}</string>
                    <key>animationsX</key>
                    <array/>
                    <key>animationsY</key>
                    <array/>
                </dict>
                <key>Rotation</key>
                <dict>
                    <key>animations</key>
                    <array/>
                </dict>
                <key>Scale</key>
                <dict>
                    <key>value</key>
                    <string>{0.700,0.700}</string>
                    <key>useDefault</key>
                    <string>0</string>
                    <key>animationsX</key>
                    <array/>
                    <key>animationsY</key>
                    <array/>
                </dict>
                <key>Hidden</key>
                <dict>
                    <key>visible</key>
                    <string>0</string>
                </dict>
                <key>Locked</key>
                <dict>
                    <key>visible</key>
                    <string>0</string>
                </dict>
                <key>Opacity</key>
                <dict>
                    <key>animations</key>
                    <array/>
                </dict>
                <key>Stick To Edge</key>
                <dict>
                    <key>value</key>
                    <string>0</string>
                </dict>
                <key>zDepth</key>
                <string>0</string>
            </dict>
            <dict>
                <key>id</key>
                <string>7437</string>
                <key>className</key>
                <string>PTModelObjectImage</string>
                <key>Name</key>
                <dict>
                    <key>value</key>
                    <string>Untitled</string>
                </dict>
                <key>Position</key>
                <dict>
                    <key>value</key>
                    <string>{0.000,0.000}</string>
                    <key>animationsX</key>
                    <array/>
                    <key>animationsY</key>
                    <array/>
                </dict>
                <key>Rotation</key>
                <dict>
                    <key>animations</key>
                    <array/>
                </dict>
                <key>Scale</key>
                <dict>
                    <key>value</key>
                    <string>{1.000,1.000}</string>
                    <key>animationsX</key>
                    <array/>
                    <key>animationsY</key>
                    <array/>
                </dict>
                <key>Hidden</key>
                <dict>
                    <key>visible</key>
                    <string>0</string>
                </dict>
                <key>Locked</key>
                <dict>
                    <key>visible</key>
                    <string>0</string>
                </dict>
                <key>Opacity</key>
                <dict>
                    <key>animations</key>
                    <array/>
                </dict>
                <key>Stick To Edge</key>
                <dict>
                    <key>value</key>
                    <string>0</string>
                </dict>
                <key>zDepth</key>
                <string>0</string>
            </dict>
            <dict>
                <key>id</key>
                <string>7446</string>
                <key>className</key>
                <string>PTModelObjectImage</string>
                <key>Name</key>
                <dict>
                    <key>value</key>
                    <string>Untitled</string>
                </dict>
                <key>Position</key>
                <dict>
                    <key>value</key>
                    <string>{0.000,0.000}</string>
                    <key>animationsX</key>
                    <array/>
                    <key>animationsY</key>
                    <array/>
                </dict>
                <key>Rotation</key>
                <dict>
                    <key>animations</key>
                    <array/>
                </dict>
                <key>Scale</key>
                <dict>
                    <key>value</key>
                    <string>{1.000,1.000}</string>
                    <key>animationsX</key>
                    <array/>
                    <key>animationsY</key>
                    <array/>
                </dict>
                <key>Hidden</key>
                <dict>
                    <key>visible</key>
                    <string>0</string>
                </dict>
                <key>Locked</key>
                <dict>
                    <key>visible</key>
                    <string>0</string>
                </dict>
                <key>Opacity</key>
                <dict>
                    <key>animations</key>
                    <array/>
                </dict>
                <key>Stick To Edge</key>
                <dict>
                    <key>value</key>
                    <string>0</string>
                </dict>
                <key>zDepth</key>
                <string>0</string>
            </dict>
            <dict>
                <key>id</key>
                <string>8200</string>
                <key>className</key>
                <string>PTModelObjectImage</string>
                <key>Name</key>
                <dict>
                    <key>value</key>
                    <string>Untitled 2</string>
                </dict>
                <key>Position</key>
                <dict>
                    <key>value</key>
                    <string>{939.775,245.508}</string>
                    <key>animationsX</key>
                    <array/>
                    <key>animationsY</key>
                    <array/>
                </dict>
                <key>Rotation</key>
                <dict>
                    <key>animations</key>
                    <array/>
                </dict>
                <key>Scale</key>
                <dict>
                    <key>value</key>
                    <string>{1.000,1.000}</string>
                    <key>animationsX</key>
                    <array/>
                    <key>animationsY</key>
                    <array/>
                </dict>
                <key>Hidden</key>
                <dict>
                    <key>visible</key>
                    <string>0</string>
                </dict>
                <key>Locked</key>
                <dict>
                    <key>visible</key>
                    <string>0</string>
                </dict>
                <key>Opacity</key>
                <dict>
                    <key>animations</key>
                    <array/>
                </dict>
                <key>zDepth</key>
                <string>3</string>
            </dict>
            <dict>
                <key>id</key>
                <string>8206</string>
                <key>className</key>
                <string>PTModelObjectImage</string>
                <key>Name</key>
                <dict>
                    <key>value</key>
                    <string>Untitled 3</string>
                </dict>
                <key>Position</key>
                <dict>
                    <key>value</key>
                    <string>{563.462,462.844}</string>
                    <key>animationsX</key>
                    <array/>
                    <key>animationsY</key>
                    <array/>
                </dict>
                <key>Rotation</key>
                <dict>
                    <key>animations</key>
                    <array/>
                </dict>
                <key>Scale</key>
                <dict>
                    <key>value</key>
                    <string>{0.763,0.763}</string>
                    <key>animationsX</key>
                    <array/>
                    <key>animationsY</key>
                    <array/>
                </dict>
                <key>Hidden</key>
                <dict>
                    <key>visible</key>
                    <string>0</string>
                </dict>
                <key>Locked</key>
                <dict>
                    <key>visible</key>
                    <string>0</string>
                </dict>
                <key>Opacity</key>
                <dict>
                    <key>animations</key>
                    <array/>
                </dict>
                <key>zDepth</key>
                <string>2</string>
            </dict>
            <dict>
                <key>id</key>
                <string>8211</string>
                <key>className</key>
                <string>PTModelObjectImage</string>
                <key>Name</key>
                <dict>
                    <key>value</key>
                    <string>Untitled 4</string>
                </dict>
                <key>Position</key>
                <dict>
                    <key>value</key>
                    <string>{597.202,230.101}</string>
                    <key>animationsX</key>
                    <array/>
                    <key>animationsY</key>
                    <array/>
                </dict>
                <key>Rotation</key>
                <dict>
                    <key>animations</key>
                    <array/>
                </dict>
                <key>Scale</key>
                <dict>
                    <key>value</key>
                    <string>{1.000,1.000}</string>
                    <key>animationsX</key>
                    <array/>
                    <key>animationsY</key>
                    <array/>
                </dict>
                <key>Hidden</key>
                <dict>
                    <key>visible</key>
                    <string>0</string>
                </dict>
                <key>Locked</key>
                <dict>
                    <key>visible</key>
                    <string>0</string>
                </dict>
                <key>Opacity</key>
                <dict>
                    <key>animations</key>
                    <array/>
                </dict>
                <key>zDepth</key>
                <string>0</string>
            </dict>
            <dict>
                <key>id</key>
                <string>8220</string>
                <key>className</key>
                <string>PTModelObjectImage</string>
                <key>Name</key>
                <dict>
                    <key>value</key>
                    <string>Untitled 2</string>
                </dict>
                <key>Position</key>
                <dict>
                    <key>value</key>
                    <string>{495.042,238.665}</string>
                    <key>animationsX</key>
                    <array/>
                    <key>animationsY</key>
                    <array/>
                </dict>
                <key>Rotation</key>
                <dict>
                    <key>animations</key>
                    <array/>
                </dict>
                <key>Scale</key>
                <dict>
                    <key>value</key>
                    <string>{1.000,1.000}</string>
                    <key>animationsX</key>
                    <array/>
                    <key>animationsY</key>
                    <array/>
                </dict>
                <key>Hidden</key>
                <dict>
                    <key>visible</key>
                    <string>0</string>
                </dict>
                <key>Locked</key>
                <dict>
                    <key>visible</key>
                    <string>0</string>
                </dict>
                <key>zDepth</key>
                <string>0</string>
            </dict>
            <dict>
                <key>id</key>
                <string>8225</string>
                <key>className</key>
                <string>PTModelObjectImage</string>
                <key>Name</key>
                <dict>
                    <key>value</key>
                    <string>Untitled 3</string>
                </dict>
                <key>Position</key>
                <dict>
                    <key>value</key>
                    <string>{549.376,478.943}</string>
                    <key>animationsX</key>
                    <array/>
                    <key>animationsY</key>
                    <array/>
                </dict>
                <key>Rotation</key>
                <dict>
                    <key>animations</key>
                    <array/>
                </dict>
                <key>Scale</key>
                <dict>
                    <key>value</key>
                    <string>{0.757,0.757}</string>
                    <key>animationsX</key>
                    <array/>
                    <key>animationsY</key>
                    <array/>
                </dict>
                <key>Hidden</key>
                <dict>
                    <key>visible</key>
                    <string>0</string>
                </dict>
                <key>Locked</key>
                <dict>
                    <key>visible</key>
                    <string>0</string>
                </dict>
                <key>zDepth</key>
                <string>1</string>
            </dict>
            <dict>
                <key>id</key>
                <string>8404</string>
                <key>className</key>
                <string>PTModelObjectImage</string>
                <key>Name</key>
                <dict>
                    <key>value</key>
                    <string>Untitled 4</string>
                </dict>
                <key>Position</key>
                <dict>
                    <key>value</key>
                    <string>{2064.475,291.793}</string>
                    <key>animationsX</key>
                    <array/>
                    <key>animationsY</key>
                    <array/>
                </dict>
                <key>Rotation</key>
                <dict>
                    <key>animations</key>
                    <array/>
                </dict>
                <key>Scale</key>
                <dict>
                    <key>value</key>
                    <string>{1.000,1.000}</string>
                    <key>animationsX</key>
                    <array/>
                    <key>animationsY</key>
                    <array/>
                </dict>
                <key>Hidden</key>
                <dict>
                    <key>visible</key>
                    <string>0</string>
                </dict>
                <key>Locked</key>
                <dict>
                    <key>visible</key>
                    <string>0</string>
                </dict>
                <key>Opacity</key>
                <dict>
                    <key>animations</key>
                    <array/>
                </dict>
                <key>zDepth</key>
                <string>1</string>
            </dict>
            <dict>
                <key>id</key>
                <string>8411</string>
                <key>className</key>
                <string>PTModelObjectImage</string>
                <key>Name</key>
                <dict>
                    <key>value</key>
                    <string>Untitled 2</string>
                </dict>
                <key>Position</key>
                <dict>
                    <key>value</key>
                    <string>{571.512,317.954}</string>
                    <key>animationsX</key>
                    <array/>
                    <key>animationsY</key>
                    <array/>
                </dict>
                <key>Rotation</key>
                <dict>
                    <key>animations</key>
                    <array/>
                </dict>
                <key>Scale</key>
                <dict>
                    <key>value</key>
                    <string>{1.000,1.000}</string>
                    <key>animationsX</key>
                    <array/>
                    <key>animationsY</key>
                    <array/>
                </dict>
                <key>Hidden</key>
                <dict>
                    <key>visible</key>
                    <string>0</string>
                </dict>
                <key>Locked</key>
                <dict>
                    <key>visible</key>
                    <string>0</string>
                </dict>
                <key>Opacity</key>
                <dict>
                    <key>animations</key>
                    <array/>
                </dict>
                <key>zDepth</key>
                <string>6</string>
            </dict>
            <dict>
                <key>id</key>
                <string>8416</string>
                <key>className</key>
                <string>PTModelObjectImage</string>
                <key>Name</key>
                <dict>
                    <key>value</key>
                    <string>Untitled 3</string>
                </dict>
                <key>Position</key>
                <dict>
                    <key>value</key>
                    <string>{565.475,489.005}</string>
                    <key>animationsX</key>
                    <array/>
                    <key>animationsY</key>
                    <array/>
                </dict>
                <key>Rotation</key>
                <dict>
                    <key>animations</key>
                    <array/>
                </dict>
                <key>Scale</key>
                <dict>
                    <key>value</key>
                    <string>{0.768,0.768}</string>
                    <key>animationsX</key>
                    <array/>
                    <key>animationsY</key>
                    <array/>
                </dict>
                <key>Hidden</key>
                <dict>
                    <key>visible</key>
                    <string>0</string>
                </dict>
                <key>Locked</key>
                <dict>
                    <key>visible</key>
                    <string>0</string>
                </dict>
                <key>Opacity</key>
                <dict>
                    <key>animations</key>
                    <array/>
                </dict>
                <key>zDepth</key>
                <string>3</string>
            </dict>
            <dict>
                <key>id</key>
                <string>8423</string>
                <key>className</key>
                <string>PTModelObjectImage</string>
                <key>Name</key>
                <dict>
                    <key>value</key>
                    <string>Untitled 4</string>
                </dict>
                <key>Position</key>
                <dict>
                    <key>value</key>
                    <string>{571.512,253.558}</string>
                    <key>animationsX</key>
                    <array/>
                    <key>animationsY</key>
                    <array/>
                </dict>
                <key>Rotation</key>
                <dict>
                    <key>animations</key>
                    <array/>
                </dict>
                <key>Scale</key>
                <dict>
                    <key>value</key>
                    <string>{1.000,1.000}</string>
                    <key>animationsX</key>
                    <array/>
                    <key>animationsY</key>
                    <array/>
                </dict>
                <key>Hidden</key>
                <dict>
                    <key>visible</key>
                    <string>0</string>
                </dict>
                <key>Locked</key>
                <dict>
                    <key>visible</key>
                    <string>0</string>
                </dict>
                <key>Opacity</key>
                <dict>
                    <key>animations</key>
                    <array/>
                </dict>
                <key>zDepth</key>
                <string>1</string>
            </dict>
            <dict>
                <key>id</key>
                <string>8433</string>
                <key>className</key>
                <string>PTModelObjectImage</string>
                <key>Name</key>
                <dict>
                    <key>value</key>
                    <string>Untitled 2</string>
                </dict>
                <key>Position</key>
                <dict>
                    <key>value</key>
                    <string>{565.474,167.026}</string>
                    <key>animationsX</key>
                    <array/>
                    <key>animationsY</key>
                    <array/>
                </dict>
                <key>Rotation</key>
                <dict>
                    <key>animations</key>
                    <array/>
                </dict>
                <key>Scale</key>
                <dict>
                    <key>value</key>
                    <string>{1.000,1.000}</string>
                    <key>animationsX</key>
                    <array/>
                    <key>animationsY</key>
                    <array/>
                </dict>
                <key>Hidden</key>
                <dict>
                    <key>visible</key>
                    <string>0</string>
                </dict>
                <key>Locked</key>
                <dict>
                    <key>visible</key>
                    <string>0</string>
                </dict>
                <key>Opacity</key>
                <dict>
                    <key>animations</key>
                    <array/>
                </dict>
                <key>zDepth</key>
                <string>0</string>
            </dict>
            <dict>
                <key>id</key>
                <string>8438</string>
                <key>className</key>
                <string>PTModelObjectImage</string>
                <key>Name</key>
                <dict>
                    <key>value</key>
                    <string>Untitled 3</string>
                </dict>
                <key>Position</key>
                <dict>
                    <key>value</key>
                    <string>{553.400,386.374}</string>
                    <key>animationsX</key>
                    <array/>
                    <key>animationsY</key>
                    <array/>
                </dict>
                <key>Rotation</key>
                <dict>
                    <key>animations</key>
                    <array/>
                </dict>
                <key>Scale</key>
                <dict>
                    <key>value</key>
                    <string>{0.775,0.775}</string>
                    <key>animationsX</key>
                    <array/>
                    <key>animationsY</key>
                    <array/>
                </dict>
                <key>Hidden</key>
                <dict>
                    <key>visible</key>
                    <string>0</string>
                </dict>
                <key>Locked</key>
                <dict>
                    <key>visible</key>
                    <string>0</string>
                </dict>
                <key>Opacity</key>
                <dict>
                    <key>animations</key>
                    <array/>
                </dict>
                <key>zDepth</key>
                <string>1</string>
            </dict>
            <dict>
                <key>id</key>
                <string>8550</string>
                <key>className</key>
                <string>PTModelObjectImage</string>
                <key>Name</key>
                <dict>
                    <key>value</key>
                    <string>PTModelSprite_ID71305</string>
                </dict>
                <key>Position</key>
                <dict>
                    <key>value</key>
                    <string>{0.000,0.000}</string>
                    <key>animationsX</key>
                    <array/>
                    <key>animationsY</key>
                    <array/>
                </dict>
                <key>Rotation</key>
                <dict>
                    <key>animations</key>
                    <array/>
                </dict>
                <key>Scale</key>
                <dict>
                    <key>value</key>
                    <string>{1.000,1.000}</string>
                    <key>animationsX</key>
                    <array/>
                    <key>animationsY</key>
                    <array/>
                </dict>
                <key>Hidden</key>
                <dict>
                    <key>visible</key>
                    <string>0</string>
                </dict>
                <key>Locked</key>
                <dict>
                    <key>visible</key>
                    <string>0</string>
                </dict>
                <key>Opacity</key>
                <dict>
                    <key>animations</key>
                    <array/>
                </dict>
                <key>Stick To Edge</key>
                <dict>
                    <key>value</key>
                    <string>0</string>
                </dict>
                <key>zDepth</key>
                <string>0</string>
            </dict>
            <dict>
                <key>id</key>
                <string>8571</string>
                <key>className</key>
                <string>PTModelObjectImage</string>
                <key>Name</key>
                <dict>
                    <key>value</key>
                    <string>PTModelSprite_ID71329</string>
                </dict>
                <key>Position</key>
                <dict>
                    <key>value</key>
                    <string>{0.000,0.000}</string>
                    <key>animationsX</key>
                    <array/>
                    <key>animationsY</key>
                    <array/>
                </dict>
                <key>Rotation</key>
                <dict>
                    <key>animations</key>
                    <array/>
                </dict>
                <key>Scale</key>
                <dict>
                    <key>value</key>
                    <string>{1.000,1.000}</string>
                    <key>animationsX</key>
                    <array/>
                    <key>animationsY</key>
                    <array/>
                </dict>
                <key>Hidden</key>
                <dict>
                    <key>visible</key>
                    <string>0</string>
                </dict>
                <key>Locked</key>
                <dict>
                    <key>visible</key>
                    <string>0</string>
                </dict>
                <key>Opacity</key>
                <dict>
                    <key>animations</key>
                    <array/>
                </dict>
                <key>Stick To Edge</key>
                <dict>
                    <key>value</key>
                    <string>0</string>
                </dict>
                <key>zDepth</key>
                <string>0</string>
            </dict>
            <dict>
                <key>id</key>
                <string>8612</string>
                <key>className</key>
                <string>PTModelObjectImage</string>
                <key>Name</key>
                <dict>
                    <key>value</key>
                    <string>PTModelSprite_ID71284</string>
                </dict>
                <key>Position</key>
                <dict>
                    <key>value</key>
                    <string>{0.000,0.000}</string>
                    <key>animationsX</key>
                    <array/>
                    <key>animationsY</key>
                    <array/>
                </dict>
                <key>Rotation</key>
                <dict>
                    <key>animations</key>
                    <array/>
                </dict>
                <key>Scale</key>
                <dict>
                    <key>value</key>
                    <string>{1.000,1.000}</string>
                    <key>animationsX</key>
                    <array/>
                    <key>animationsY</key>
                    <array/>
                </dict>
                <key>Hidden</key>
                <dict>
                    <key>visible</key>
                    <string>0</string>
                </dict>
                <key>Locked</key>
                <dict>
                    <key>visible</key>
                    <string>0</string>
                </dict>
                <key>Opacity</key>
                <dict>
                    <key>animations</key>
                    <array/>
                </dict>
                <key>Stick To Edge</key>
                <dict>
                    <key>value</key>
                    <string>0</string>
                </dict>
                <key>zDepth</key>
                <string>0</string>
            </dict>
            <dict>
                <key>id</key>
                <string>8737</string>
                <key>className</key>
                <string>PTModelObjectImage</string>
                <key>Name</key>
                <dict>
                    <key>value</key>
                    <string>Untitled 4</string>
                </dict>
                <key>Position</key>
                <dict>
                    <key>value</key>
                    <string>{172.738,273.208}</string>
                    <key>animationsX</key>
                    <array/>
                    <key>animationsY</key>
                    <array/>
                </dict>
                <key>Rotation</key>
                <dict>
                    <key>animations</key>
                    <array/>
                </dict>
                <key>Scale</key>
                <dict>
                    <key>value</key>
                    <string>{0.550,0.550}</string>
                    <key>animationsX</key>
                    <array/>
                    <key>animationsY</key>
                    <array/>
                </dict>
                <key>Hidden</key>
                <dict>
                    <key>visible</key>
                    <string>0</string>
                </dict>
                <key>Locked</key>
                <dict>
                    <key>visible</key>
                    <string>0</string>
                </dict>
                <key>zDepth</key>
                <string>4</string>
            </dict>
        </array>
    </dict>
</plist>
